{
  "parent": "minecraft:recipes/root",
  "rewards": {
    "recipes": [
      "projectdinosaur:items/syringe"
    ]
  },
  "criteria": {
    "iron_ingot": {
      "trigger": "minecraft:inventory_changed",
      "conditions": {
        "items": [
          {
            "items": [
              "minecraft:iron_ingot"
            ]
          }
        ]
      }
    },
    "has_the_recipe": {
      "trigger": "minecraft:recipe_unlocked",
      "conditions": {
        "recipe": "projectdinosaur:items/syringe"
      }
    }
  },
  "requirements": [
    [
      "iron_ingot",
      "has_the_recipe"
    ]
  ]
}